ascetic_ddd/__init__.py
ascetic_ddd/deferred/__init__.py
ascetic_ddd/deferred/deferred.py
ascetic_ddd/deferred/interfaces.py
ascetic_ddd/disposable/__init__.py
ascetic_ddd/disposable/disposable.py
ascetic_ddd/disposable/interfaces.py
ascetic_ddd/event_bus/__init__.py
ascetic_ddd/event_bus/in_memory_event_bus.py
ascetic_ddd/event_bus/interfaces.py
ascetic_ddd/factory.py
ascetic_ddd/faker/README_RU.md
ascetic_ddd/faker/__init__.py
ascetic_ddd/faker/domain/__init__.py
ascetic_ddd/faker/domain/distributors/__init__.py
ascetic_ddd/faker/domain/distributors/m2o/__init__.py
ascetic_ddd/faker/domain/distributors/m2o/cursor.py
ascetic_ddd/faker/domain/distributors/m2o/dummy_distributor.py
ascetic_ddd/faker/domain/distributors/m2o/factory.py
ascetic_ddd/faker/domain/distributors/m2o/interfaces.py
ascetic_ddd/faker/domain/distributors/m2o/nullable_distributor.py
ascetic_ddd/faker/domain/distributors/m2o/sequence_distributor.py
ascetic_ddd/faker/domain/distributors/m2o/skew_distributor.py
ascetic_ddd/faker/domain/distributors/m2o/weighted_distributor.py
ascetic_ddd/faker/domain/distributors/o2m/__init__.py
ascetic_ddd/faker/domain/distributors/o2m/distribution_distributor.py
ascetic_ddd/faker/domain/distributors/o2m/interfaces.py
ascetic_ddd/faker/domain/distributors/o2m/range_distributor_adapter.py
ascetic_ddd/faker/domain/distributors/o2m/skew_distributor.py
ascetic_ddd/faker/domain/distributors/o2m/weighted_distributor.py
ascetic_ddd/faker/domain/distributors/o2m/weighted_range_distributor.py
ascetic_ddd/faker/domain/generators/__init__.py
ascetic_ddd/faker/domain/generators/generators.py
ascetic_ddd/faker/domain/generators/interfaces.py
ascetic_ddd/faker/domain/providers/__init__.py
ascetic_ddd/faker/domain/providers/_mixins.py
ascetic_ddd/faker/domain/providers/aggregate_provider.py
ascetic_ddd/faker/domain/providers/composite_value_provider.py
ascetic_ddd/faker/domain/providers/dependent_provider.py
ascetic_ddd/faker/domain/providers/entity_provider.py
ascetic_ddd-0.1.5.dist-info/METADATA
ascetic_ddd-0.1.5.dist-info/WHEEL
ascetic_ddd-0.1.5.dist-info/licenses/LICENSE
ascetic_ddd-0.1.5.dist-info/RECORD
